SyntaxHighlighterS/__init__.py
SyntaxHighlighterS/main.py
SyntaxHighlighterS-0.0.5.dist-info/LICENSE.txt
SyntaxHighlighterS-0.0.5.dist-info/METADATA
SyntaxHighlighterS-0.0.5.dist-info/WHEEL
SyntaxHighlighterS-0.0.5.dist-info/top_level.txt
SyntaxHighlighterS-0.0.5.dist-info/RECORD
