Metadata-Version: 2.1
Name: SyntaxHighlighterS
Version: 0.0.5
Summary: A Simple Starter Syntax Highlighter.
Author: TuberAsk
Project-URL: Homepage, https://github.com/TuberAsk/SyntaxHighlighterS
Project-URL: Documentation, https://github.com/TuberAsk/SyntaxHighlighterS/wiki
Project-URL: Funding, https://patreon.com/isitopensource
Project-URL: Bug Tracker, https://github.com/TuberAsk/SyntaxHighlighterS/issues
License-File: LICENSE.txt
